django_link-0.1.0.dist-info/DESCRIPTION.rst
django_link-0.1.0.dist-info/METADATA
django_link-0.1.0.dist-info/RECORD
django_link-0.1.0.dist-info/WHEEL
django_link-0.1.0.dist-info/metadata.json
django_link-0.1.0.dist-info/top_level.txt
link/__init__.py
link/admin.py
link/forms.py
link/models.py
link/urls.py
link/utils.py
link/views.py
link/api/__init__.py
link/migrations/0001_initial.py
link/migrations/0002_auto_20160902_0249.py
link/migrations/__init__.py
link/templates/link/link_detail.html
link/templates/link/link_list.html
link/templates/link/inclusion_tags/link_detail.html
link/templatetags/__init__.py
link/templatetags/link_tags.py
link/tests/__init__.py
link/tests/test_admin.py
link/tests/test_forms.py
link/tests/test_models.py
link/tests/test_utils.py
link/tests/test_views.py
link/tests/urls.py
link/tests/views.py
link/tests/requirements/110.txt
link/tests/requirements/19.txt
link/tests/settings/110.py
link/tests/settings/19.py
link/tests/settings/__init__.py
link/tests/templates/base.html
