Metadata-Version: 2.0
Name: django-link
Version: 0.1.0
Summary: Modeled link objects which include linking to objects, views and static urls.
Home-page: http://github.com/praekelt/django-link
Author: Praekelt Consulting
Author-email: dev@praekelt.com
License: BSD
Platform: UNKNOWN
Classifier: Programming Language :: Python
Classifier: License :: OSI Approved :: BSD License
Classifier: Operating System :: OS Independent
Classifier: Framework :: Django
Classifier: Intended Audience :: Developers
Classifier: Topic :: Internet :: WWW/HTTP :: Dynamic Content
Requires-Dist: django
